debpkgr/__init__.py
debpkgr/aptrepo.py
debpkgr/compat.py
debpkgr/compressr.py
debpkgr/constants.py
debpkgr/debpkg.py
debpkgr/errors.py
debpkgr/hasher.py
debpkgr/signer.py
debpkgr/utils.py
debpkgr-1.0.1.dist-info/DESCRIPTION.rst
debpkgr-1.0.1.dist-info/METADATA
debpkgr-1.0.1.dist-info/RECORD
debpkgr-1.0.1.dist-info/WHEEL
debpkgr-1.0.1.dist-info/metadata.json
debpkgr-1.0.1.dist-info/pbr.json
debpkgr-1.0.1.dist-info/top_level.txt
