Metadata-Version: 2.0
Name: debpkgr
Version: 1.0.1
Summary: Debian/Ubuntu .deb pkg utils
Home-page: https://github.com/sassoftware/python-debpkgr
Author: Brett Smith
Author-email: bc.smith@sas.com
License: UNKNOWN
Platform: UNKNOWN
Classifier: Development Status :: 4 - Beta
Classifier: Intended Audience :: Developers
Classifier: Intended Audience :: Information Technology
Classifier: License :: OSI Approved :: Apache Software License
Classifier: Operating System :: Microsoft :: Windows
Classifier: Operating System :: Unix
Classifier: Programming Language :: Python :: 2.7
Classifier: Programming Language :: Python :: 3.4
Classifier: Programming Language :: Python :: 3.5
Requires-Dist: chardet (~=2.3.0)
Requires-Dist: python-debian (~=0.1.28)
Requires-Dist: six (~=1.0)
Requires-Dist: backports.lzma (~=0.0); (python_version<'3.3')
Provides-Extra: development
Requires-Dist: epdb (~=0.0); extra == 'development'
Requires-Dist: flake8 (~=3.0); extra == 'development'
Requires-Dist: tox (~=2.0); extra == 'development'
Provides-Extra: testing
Requires-Dist: pytest; extra == 'testing'
Requires-Dist: pytest-cov; extra == 'testing'
Provides-Extra: testing
Requires-Dist: mock; (python_version<'3.4') and extra == 'testing'
